lichess/__init__.py
lichess/api.py
lichess/auth.py
lichess/format.py
lichess/pgn.py
python_lichess-0.10.dist-info/LICENSE.txt
python_lichess-0.10.dist-info/METADATA
python_lichess-0.10.dist-info/WHEEL
python_lichess-0.10.dist-info/top_level.txt
python_lichess-0.10.dist-info/RECORD
