Metadata-Version: 1.2
Name: python-lichess
Version: 0.10
Summary: A client for the lichess.org API
Home-page: https://github.com/cyanfish/python-lichess
License: GPL3
Keywords: chess lichess api
Platform: UNKNOWN
Classifier: Development Status :: 4 - Beta
Classifier: Intended Audience :: Developers
Classifier: Intended Audience :: Science/Research
Classifier: License :: OSI Approved :: GNU General Public License v3 or later (GPLv3+)
Classifier: Operating System :: OS Independent
Classifier: Programming Language :: Python
Classifier: Programming Language :: Python :: 2
Classifier: Programming Language :: Python :: 2.7
Classifier: Programming Language :: Python :: 3
Classifier: Programming Language :: Python :: 3.3
Classifier: Programming Language :: Python :: 3.4
Classifier: Programming Language :: Python :: 3.5
Classifier: Programming Language :: Python :: 3.6
Classifier: Topic :: Games/Entertainment :: Board Games
Classifier: Topic :: Software Development :: Libraries :: Python Modules
Requires-Python: >=2.7,!=3.0.*,!=3.1.*,!=3.2.*
